{
  "run_id": "20251116_224035",
  "timestamp": "2025-11-16T22:40:36.238322+00:00",
  "symbol": "USDJPY",
  "csv_path": "results/walkforward_usdjpy_xgb_short_v1e_20251116_224027/walkforward/window_011_test.csv",
  "parameters": {
    "fast_win": 20,
    "slow_win": 80,
    "spread_pips": 2.0,
    "commission_per_million": 0.25,
    "slippage_pips": 0.3,
    "stop_loss_pips": 50,
    "take_profit_pips": null,
    "atr_sl": 1.9,
    "atr_tp": 3.8,
    "atr_window": 14,
    "rsi_period": 14,
    "regime_ema_window": 200,
    "skip_outlier_entries": false,
    "strategy_mode": "first_hit",
    "strategy_vote_threshold": 0.0,
    "stress_cost_spread_mult": 1.0,
    "stress_cost_comm_mult": 1.0,
    "stress_slippage_mult": 1.0,
    "stress_price_vol_mult": 1.0,
    "stress_skip_trade_pct": 0.0
  },
  "metrics": {
    "fast": 20,
    "slow": 80,
    "final_equity": 960236.298350635,
    "ann_return": 0.000994075966620711,
    "ann_vol": 0.0010859469224277461,
    "sharpe": 0.9154001416554982,
    "max_drawdown": -0.00042820168847153414,
    "sortino": 0.4033167499390802,
    "calmar": 2.3215134208579724,
    "max_drawdown_duration_bars": 919,
    "avg_drawdown_duration_bars": 13.357142857142858,
    "current_drawdown_duration_bars": 919,
    "recovery_time_bars": 919,
    "trades": 26,
    "atr_sl": 1.9,
    "atr_tp": 3.8,
    "atr_window": 14
  },
  "data_report": null,
  "artifacts": {
    "equity": "data/outputs/equity/equity_USDJPY_H1_20x80_ATR1.9x3.8_W14_ABOVE_SHORT_BELOW.csv",
    "trades": "data/outputs/trades/trades_USDJPY_20251116_224036.csv",
    "trade_stats": "data/outputs/stats/stats_USDJPY_H1_20x80_ATR1.9x3.8_W14_ABOVE_SHORT_BELOW.json"
  }
}